armcor/__init__.py
armcor/ocr.py
armcor/combo/encoders.py
armcor/combo/main.py
armcor/combo/models.py
armcor/combo/mst.py
armcor/combo/parser.py
armcor/combo/utils.py
armcor-0.2.dist-info/METADATA
armcor-0.2.dist-info/WHEEL
armcor-0.2.dist-info/top_level.txt
armcor-0.2.dist-info/RECORD
